otel/django/middleware/__init__.py
otel/django/middleware/package.py
otel/django/middleware/version.py
otel_django_middleware-0.1.dist-info/METADATA
otel_django_middleware-0.1.dist-info/WHEEL
otel_django_middleware-0.1.dist-info/RECORD
