Metadata-Version: 2.1
Name: otel-django-middleware
Version: 0.1
Summary: OpenTelemetry Instrumentation for tracing Django Middleware
Author-email: Hyrum Nantais <hyrumaknantais@gmail.com>
Classifier: Development Status :: 4 - Beta
Classifier: Intended Audience :: Developers
Classifier: Programming Language :: Python
Classifier: Programming Language :: Python :: 3
Classifier: Programming Language :: Python :: 3.7
Classifier: Programming Language :: Python :: 3.8
Classifier: Programming Language :: Python :: 3.9
Classifier: Programming Language :: Python :: 3.10
Classifier: Programming Language :: Python :: 3.11
Requires-Python: >=3.7
Requires-Dist: opentelemetry-instrumentation-django==0.38b0
Provides-Extra: instruments
Requires-Dist: django>=1.10; extra == 'instruments'
